hpsdecode/__init__.py
hpsdecode/binary.py
hpsdecode/commands.py
hpsdecode/encryption.py
hpsdecode/exceptions.py
hpsdecode/loader.py
hpsdecode/mesh.py
hpsdecode/py.typed
hpsdecode/schemas/__init__.py
hpsdecode/schemas/base.py
hpsdecode/schemas/ca.py
hpsdecode/schemas/cb.py
hpsdecode/schemas/cc.py
hpsdecode/schemas/ce.py
hpsdecode-0.1.0.dist-info/WHEEL
hpsdecode-0.1.0.dist-info/METADATA
hpsdecode-0.1.0.dist-info/RECORD
