Metadata-Version: 2.3
Name: hpsdecode
Version: 0.1.0
Summary: A library for decoding HIMSA packed standard (HPS) files.
Author: HeadTriXz
License: MIT License
Classifier: Development Status :: 3 - Alpha
Classifier: Programming Language :: Python :: 3
Classifier: Programming Language :: Python :: 3.10
Classifier: Programming Language :: Python :: 3.11
Classifier: Programming Language :: Python :: 3.12
Classifier: Programming Language :: Python :: 3.13
Classifier: Programming Language :: Python :: 3.14
Classifier: Operating System :: OS Independent
Classifier: License :: OSI Approved :: MIT License
Classifier: Intended Audience :: Developers
Classifier: Intended Audience :: Science/Research
Classifier: Topic :: File Formats
Classifier: Topic :: Multimedia :: Graphics
Classifier: Topic :: Multimedia :: Graphics :: 3D Modeling
Classifier: Topic :: Scientific/Engineering
Requires-Dist: numpy>=2.2.6
Requires-Dist: pycryptodome>=3.23.0
Requires-Dist: ruff>=0.14.6 ; extra == 'dev'
Requires-Python: >=3.10
Project-URL: Homepage, https://github.com/HeadTriXz/hpsdecode
Project-URL: Issues, https://github.com/HeadTriXz/hpsdecode/issues
Provides-Extra: dev
